MANIFEST.in
README.rst
setup.cfg
setup.py
docs/CONTRIBUTORS.rst
docs/HISTORY.rst
docs/INSTALL.txt
docs/LICENSE.GPL
docs/LICENSE.txt
seantis/__init__.py
seantis.dir.eventsportlet.egg-info/PKG-INFO
seantis.dir.eventsportlet.egg-info/SOURCES.txt
seantis.dir.eventsportlet.egg-info/dependency_links.txt
seantis.dir.eventsportlet.egg-info/entry_points.txt
seantis.dir.eventsportlet.egg-info/namespace_packages.txt
seantis.dir.eventsportlet.egg-info/not-zip-safe
seantis.dir.eventsportlet.egg-info/requires.txt
seantis.dir.eventsportlet.egg-info/top_level.txt
seantis/dir/__init__.py
seantis/dir/eventsportlet/__init__.py
seantis/dir/eventsportlet/configure.zcml
seantis/dir/eventsportlet/events.pt
seantis/dir/eventsportlet/events.py
seantis/dir/eventsportlet/sync.sh
seantis/dir/eventsportlet/upgrades.py
seantis/dir/eventsportlet/css/events.css
seantis/dir/eventsportlet/js/events.js
seantis/dir/eventsportlet/locales/manual.pot
seantis/dir/eventsportlet/locales/plone.pot
seantis/dir/eventsportlet/locales/seantis.dir.eventsportlet.pot
seantis/dir/eventsportlet/locales/de/LC_MESSAGES/plone.po
seantis/dir/eventsportlet/locales/de/LC_MESSAGES/seantis.dir.eventsportlet.po
seantis/dir/eventsportlet/profiles/default/cssregistry.xml
seantis/dir/eventsportlet/profiles/default/jsregistry.xml
seantis/dir/eventsportlet/profiles/default/metadata.xml
seantis/dir/eventsportlet/profiles/default/portlets.xml
seantis/dir/eventsportlet/tests/__init__.py
seantis/dir/eventsportlet/tests/layer.py
seantis/dir/eventsportlet/tests/test_portlet.py
seantis/dir/eventsportlet/tests/test_portlet_browser.py