Metadata-Version: 1.1
Name: seantis.dir.eventsportlet
Version: 1.2
Summary: Portlet for displaying events.
Home-page: https://github.com/seantis/seantis.dir.eventsportlet
Author: Seantis GmbH
Author-email: info@seantis.ch
License: GPL
Platform: UNKNOWN
Classifier: Framework :: Plone
Classifier: Programming Language :: Python
